boss/__init__.py
boss/__main__.py
boss/call_bo.py
boss/bo/__init__.py
boss/bo/bo_main.py
boss/bo/hmc.py
boss/bo/kernel_factory.py
boss/bo/model.py
boss/bo/acq/__init__.py
boss/bo/acq/ei.py
boss/bo/acq/elcb.py
boss/bo/acq/exploit.py
boss/bo/acq/explore.py
boss/bo/acq/lcb.py
boss/io/__init__.py
boss/io/data_output.py
boss/io/ioutils.py
boss/io/main_output.py
boss/io/parse.py
boss/io/settings.py
boss/mep/__init__.py
boss/mep/forest.py
boss/mep/mep.py
boss/mep/mepmain.py
boss/mep/neb.py
boss/mep/node.py
boss/mep/path.py
boss/mep/space.py
boss/pp/__init__.py
boss/pp/plot.py
boss/pp/pp_main.py
boss/tests/__init__.py
boss/tests/bo_tests.py
boss/tests/pp_tests.py
boss/utils/__init__.py
boss/utils/distributions.py
boss/utils/drawpoints.py
boss/utils/initmanager.py
boss/utils/minimization.py
boss/utils/rstmanager.py
boss/utils/sobol_seq.py
boss/utils/timer.py
laos_boats-0.9.17.dist-info/LICENSE.txt
laos_boats-0.9.17.dist-info/METADATA
laos_boats-0.9.17.dist-info/WHEEL
laos_boats-0.9.17.dist-info/entry_points.txt
laos_boats-0.9.17.dist-info/top_level.txt
laos_boats-0.9.17.dist-info/RECORD
